pid/__init__.py
pid/base.py
pid/decorator.py
pid/posix.py
pid/utils.py
pid/win32.py
pid-3.0.3.dist-info/AUTHORS
pid-3.0.3.dist-info/LICENSE
pid-3.0.3.dist-info/METADATA
pid-3.0.3.dist-info/WHEEL
pid-3.0.3.dist-info/pbr.json
pid-3.0.3.dist-info/top_level.txt
pid-3.0.3.dist-info/RECORD
