Metadata-Version: 1.1
Name: pid
Version: 3.0.3
Summary: Pidfile featuring stale detection and file-locking, can also be used as context-manager or decorator
Home-page: https://github.com/trbs/pid/
Author: Trbs
Author-email: trbs@trbs.net
License: ASL
Keywords: pid pidfile context manager decorator
Platform: UNKNOWN
Classifier: Development Status :: 5 - Production/Stable
Classifier: Intended Audience :: Developers
Classifier: License :: OSI Approved :: Apache Software License
Classifier: Programming Language :: Python :: 2
Classifier: Programming Language :: Python :: 2.7
Classifier: Programming Language :: Python :: 3
Classifier: Programming Language :: Python :: 3.4
Classifier: Programming Language :: Python :: 3.5
Classifier: Programming Language :: Python :: 3.6
Classifier: Programming Language :: Python :: 3.7
Classifier: Programming Language :: Python :: 3.8
Classifier: Programming Language :: Python :: Implementation :: PyPy
